log_analyzer_client/__init__.py
log_analyzer_client/cli.py
log_analyzer_client/py.typed
log_analyzer_mcp/__init__.py
log_analyzer_mcp/log_analyzer_mcp_server.py
log_analyzer_mcp/py.typed
log_analyzer_mcp/test_log_parser.py
log_analyzer_mcp/common/__init__.py
log_analyzer_mcp/common/config_loader.py
log_analyzer_mcp/common/logger_setup.py
log_analyzer_mcp/common/utils.py
log_analyzer_mcp/core/__init__.py
log_analyzer_mcp/core/analysis_engine.py
log_analyzer_mcp-0.1.8.dist-info/METADATA
log_analyzer_mcp-0.1.8.dist-info/WHEEL
log_analyzer_mcp-0.1.8.dist-info/entry_points.txt
log_analyzer_mcp-0.1.8.dist-info/licenses/LICENSE.md
log_analyzer_mcp-0.1.8.dist-info/RECORD
