Metadata-Version: 2.4
Name: log_analyzer_mcp
Version: 0.1.8
Summary: MCP server and tools for analyzing test and runtime logs.
Project-URL: Homepage, https://github.com/nold-ai/log_analyzer_mcp
Project-URL: Repository, https://github.com/nold-ai/log_analyzer_mcp.git
Project-URL: Documentation, https://github.com/nold-ai/log_analyzer_mcp#readme
Author-email: "Dominikus Nold (Nold Coaching & Consulting)" <info@noldcoaching.de>
License: # MIT License
License-File: LICENSE.md
Keywords: coverage,development-tools,log-analysis,mcp,runtime-errors,testing
Classifier: Development Status :: 4 - Beta
Classifier: Intended Audience :: Developers
Classifier: License :: Other/Proprietary License
Classifier: Programming Language :: Python :: 3
Classifier: Programming Language :: Python :: 3.10
Classifier: Programming Language :: Python :: 3.11
Classifier: Programming Language :: Python :: 3.12
Classifier: Topic :: Software Development :: Libraries :: Python Modules
Classifier: Topic :: Software Development :: Quality Assurance
Classifier: Topic :: Software Development :: Testing
Classifier: Topic :: System :: Logging
Requires-Python: >=3.10
Requires-Dist: click>=8.2.1
Requires-Dist: jsonschema>=4.24.0
Requires-Dist: loguru>=0.7.3
Requires-Dist: mcp>=1.9.1
Requires-Dist: pydantic-core>=2.33.2
Requires-Dist: pydantic>=2.11.5
Requires-Dist: python-dateutil>=2.9.0.post0
Requires-Dist: python-dotenv>=1.1.0
Requires-Dist: pytz>=2025.2
Requires-Dist: pyyaml>=6.0.2
Requires-Dist: requests>=2.32.3
Requires-Dist: rich>=14.0.0
Requires-Dist: tenacity>=9.1.2
Requires-Dist: toml>=0.10.2
Requires-Dist: types-pyyaml>=6.0.12.20250516
Requires-Dist: typing-extensions>=4.13.2
Provides-Extra: dev
Requires-Dist: black>=25.1.0; extra == 'dev'
Requires-Dist: chroma-mcp-server[client,devtools]>=0.2.28; extra == 'dev'
Requires-Dist: isort>=6.0.1; extra == 'dev'
Requires-Dist: mypy>=1.15.0; extra == 'dev'
Requires-Dist: pylint>=3.3.7; extra == 'dev'
Requires-Dist: pytest-cov>=6.1.1; extra == 'dev'
Requires-Dist: pytest-mock>=3.14.1; extra == 'dev'
Requires-Dist: pytest>=8.3.5; extra == 'dev'
Requires-Dist: types-pyyaml>=6.0.12.20250516; extra == 'dev'
